{
  "source": "https://pan.52wei.cc/categories.php?id=4",
  "category": "软件",
  "file_index": 100,
  "total": 100,
  "items": [
    {
      "title": "小红本批量改写 v1.2.0",
      "link": "https://pan.quark.cn/s/a9c5c6c07aee"
    },
    {
      "title": "多开分身4.0.0高级版.apk",
      "link": "https://pan.quark.cn/s/fef67a9e3f4b"
    },
    {
      "title": "松子影视 1.0.2去广告.apk",
      "link": "https://pan.quark.cn/s/3c3768cd8fa1"
    },
    {
      "title": "哔哩哔哩_小米_15S_Pro_定制版_v6_56_0.apk",
      "link": "https://pan.quark.cn/s/156cb60f3b4b"
    },
    {
      "title": "搜书大师_v23.13去广告.apk",
      "link": "https://pan.quark.cn/s/06c82e9e9a25"
    },
    {
      "title": "隐秘相机 Ver.4.3.3 会员版.apk",
      "link": "https://pan.quark.cn/s/365d4fd94070"
    },
    {
      "title": "集影视频工具箱_Ver_3_8_9会员版.apk",
      "link": "https://pan.quark.cn/s/6b694ddf87cf"
    },
    {
      "title": "雨见浏览器v7.8.6清爽版.apk",
      "link": "https://pan.quark.cn/s/766c3aa01f8c"
    },
    {
      "title": "oneAnime看番工具v1.4.1绿色版",
      "link": "https://pan.quark.cn/s/1e92905467bf"
    },
    {
      "title": "开发者选项.apk",
      "link": "https://pan.quark.cn/s/21bcd6e1a5b8"
    },
    {
      "title": "李跳跳_李跳跳2.6.apk",
      "link": "https://pan.quark.cn/s/4332006ee67f"
    },
    {
      "title": "VLLO视频编辑 12.4.4高级版_Modded-1.apk",
      "link": "https://pan.quark.cn/s/8148b7849633"
    },
    {
      "title": "极速电视_6.5.2.apk",
      "link": "https://pan.quark.cn/s/ad6b78c47ad7"
    },
    {
      "title": "橙子阅读v1.5.8.apk",
      "link": "https://pan.quark.cn/s/f12669adacdd"
    },
    {
      "title": "音配v1.3.0.apk",
      "link": "https://pan.quark.cn/s/14f2d57df879"
    },
    {
      "title": "XtraTools v25.3.1.exe",
      "link": "https://pan.quark.cn/s/2f2b7784b570"
    },
    {
      "title": "我的听书v2.5.6纯净版+.apk",
      "link": "https://pan.quark.cn/s/7005dc05c2b9"
    },
    {
      "title": "Clean WeChat X微信数据深度清理v4.0.rar",
      "link": "https://pan.quark.cn/s/47bdd5bf1234"
    },
    {
      "title": "kwyinyue v11.2.8.1 破解 VIP 会员.zip",
      "link": "https://pan.quark.cn/s/0096c10d24d9"
    },
    {
      "title": "邮件群发工具.zip",
      "link": "https://pan.quark.cn/s/19b22fc4b9cf"
    },
    {
      "title": "WPS Office Premium v18.18-破解版.apk",
      "link": "https://pan.quark.cn/s/1d35e7de51da"
    },
    {
      "title": "七猫免费小说_7.74_破解版.apk",
      "link": "https://pan.quark.cn/s/1a86d7bf98b9"
    },
    {
      "title": "追剧达人 3.3.0去广告版v2_鹿蜀.apk",
      "link": "https://pan.quark.cn/s/4404cb8f346e"
    },
    {
      "title": "蛋播星球 1.0.2-250613.apk",
      "link": "https://pan.quark.cn/s/0e162ce62498"
    },
    {
      "title": "Gear_6.21.8_解锁订阅.ipa",
      "link": "https://pan.quark.cn/s/08bdb75251b0"
    },
    {
      "title": "悟空下载 v1.3.0 高级版.apk",
      "link": "https://pan.quark.cn/s/28ae010f79d3"
    },
    {
      "title": "趣映 2.7.2会员版.apk",
      "link": "https://pan.quark.cn/s/c55a5adafc0a"
    },
    {
      "title": "绘梦轩v1.0.1去广告版.apk",
      "link": "https://pan.quark.cn/s/2e686ea17cee"
    },
    {
      "title": "囧次元-1.5.7.8.apk",
      "link": "https://pan.quark.cn/s/cb39723fba25"
    },
    {
      "title": "逐浪小说-3.8.11.apk",
      "link": "https://pan.quark.cn/s/116953f4f0c9"
    },
    {
      "title": "喵呜漫画v1.0.5.apk",
      "link": "https://pan.quark.cn/s/aa4d2777c8db"
    },
    {
      "title": "冬日动漫-1.2.0.apk",
      "link": "https://pan.quark.cn/s/7a85ba35d5c6"
    },
    {
      "title": "大地视频-4.0.0.apk",
      "link": "https://pan.quark.cn/s/9b100215b63b"
    },
    {
      "title": "新星漂移.rar",
      "link": "https://pan.quark.cn/s/c6af77259544"
    },
    {
      "title": "修仙故事 无尽剑域.rar",
      "link": "https://pan.quark.cn/s/7efe0000cc22"
    },
    {
      "title": "侍道外传~刀神.rar",
      "link": "https://pan.quark.cn/s/eea0530c7c1a"
    },
    {
      "title": "独行侠 重装上阵.rar",
      "link": "https://pan.quark.cn/s/c1af8e68d04d"
    },
    {
      "title": "追剧达人 3.4.0去广告版.apk",
      "link": "https://pan.quark.cn/s/99aea1293a67"
    },
    {
      "title": "得间免费小说 5.4.2.1会员版.apk",
      "link": "https://pan.quark.cn/s/c5f52574e92c"
    },
    {
      "title": "Good Pizza",
      "link": "https://pan.quark.cn/s/fbef4fa27c20"
    },
    {
      "title": "小飞电视_v2.7.0.apk",
      "link": "https://pan.quark.cn/s/253e45dfb0a1"
    },
    {
      "title": "OurTV_我们的电视_v3_0_2_自动更新到_v3_9_5_重构版.apk",
      "link": "https://pan.quark.cn/s/8637c8365857"
    },
    {
      "title": "Player-6.1.3-exo161_内置版.apk",
      "link": "https://pan.quark.cn/s/3063b03aa8ad"
    },
    {
      "title": "Netflix MOD v9.18.4.apk",
      "link": "https://pan.quark.cn/s/5cd75f097ad7"
    },
    {
      "title": "笔趣阁全版本：经典版+完美版+红版+蓝版+黄版",
      "link": "https://pan.quark.cn/s/c73bb864674a"
    },
    {
      "title": "定位找人_8.6.1_解锁会员.zip",
      "link": "https://pan.quark.cn/s/2b06b6b526f3"
    },
    {
      "title": "防撤回消息6.5_会员版.zip",
      "link": "https://pan.quark.cn/s/b39c1f79e53a"
    },
    {
      "title": "5sing音乐_6.10.90.apk",
      "link": "https://pan.quark.cn/s/0684b59dbb5e"
    },
    {
      "title": "元气桌面壁纸_3.52.4326_解锁会员_组件.APK",
      "link": "https://pan.quark.cn/s/37bc999abe3d"
    },
    {
      "title": "小米坡 Word文档转视频生成工具 v1.16.zip",
      "link": "https://pan.quark.cn/s/94abfcfbdb3b"
    },
    {
      "title": "DuoFun Ver.1.0.2 会员版.apk",
      "link": "https://pan.quark.cn/s/74521c3403b5"
    },
    {
      "title": "若雪4K 4.0.0纯净版.apk",
      "link": "https://pan.quark.cn/s/08a46c25d729"
    },
    {
      "title": "电视家修复版10.3.0.apk",
      "link": "https://pan.quark.cn/s/ecf78371ce11"
    },
    {
      "title": "仓鼠4K_4.0.0(400).apk",
      "link": "https://pan.quark.cn/s/3ecb474cb861"
    },
    {
      "title": "双子星动漫 1.0.0去广告版_幻幻喵.apK",
      "link": "https://pan.quark.cn/s/53d11fc45101"
    },
    {
      "title": "知音漫客_6_6_42025031000_解锁限制去更新去广告.apk",
      "link": "https://pan.quark.cn/s/e3b5a8070f8e"
    },
    {
      "title": "酒店防窥检测_1.3.1.apk",
      "link": "https://pan.quark.cn/s/578470b449d4"
    },
    {
      "title": "手机电视高清直播_8.0.30.apk",
      "link": "https://pan.quark.cn/s/bab9bea1480b"
    },
    {
      "title": "全民播放_2.3.apk",
      "link": "https://pan.quark.cn/s/13f3cf7d4028"
    },
    {
      "title": "FaceJoy_1.1.8.0.apk",
      "link": "https://pan.quark.cn/s/cb0255bf562a"
    },
    {
      "title": "DreamFace_4.8.5.apk",
      "link": "https://pan.quark.cn/s/d8596325b0d2"
    },
    {
      "title": "搜图神器_5.2.4.zip",
      "link": "https://pan.quark.cn/s/abede54ac889"
    },
    {
      "title": "汽水音乐.apk",
      "link": "https://pan.quark.cn/s/42ca7529f86b"
    },
    {
      "title": "云享直播_1.0.5.apk",
      "link": "https://pan.quark.cn/s/ac7cf4bc7375"
    },
    {
      "title": "HTV-v3.5.0.apk",
      "link": "https://pan.quark.cn/s/deb68aa246c3"
    },
    {
      "title": "书旗小说_12.3.9.237.apk",
      "link": "https://pan.quark.cn/s/b5bcc595d6b1"
    },
    {
      "title": "宝宝趣学.apk",
      "link": "https://pan.quark.cn/s/2f95b8577cce"
    },
    {
      "title": "次元城动画 4.2.7去广告版_鹿蜀.apk",
      "link": "https://pan.quark.cn/s/f8141f9dc9ec"
    },
    {
      "title": "MUYTV.apk",
      "link": "https://pan.quark.cn/s/9c2c9b3d9d9f"
    },
    {
      "title": "网络电视_1.6 .apk",
      "link": "https://pan.quark.cn/s/c30b3bb1b646"
    },
    {
      "title": "全球TV_8.0_可看全球各国TV.apk",
      "link": "https://pan.quark.cn/s/b27d9275f28c"
    },
    {
      "title": "火烈鸟直播_2025.apk",
      "link": "https://pan.quark.cn/s/d63e8fbd32e2"
    },
    {
      "title": "千恋万花.zip",
      "link": "https://pan.quark.cn/s/936850b81ecc"
    },
    {
      "title": "云帆直播_1.0 .apk",
      "link": "https://pan.quark.cn/s/a64ff1b30029"
    },
    {
      "title": "Spotify_ v9.0.52.505 _破解版.apk",
      "link": "https://pan.quark.cn/s/a6c7c126f1b1"
    },
    {
      "title": "AutoJs高级版本地服务验证.zip",
      "link": "https://pan.quark.cn/s/674583794906"
    },
    {
      "title": "WePush：极简高效的跨平台批量推送工具 小而美",
      "link": "https://pan.quark.cn/s/adf93387d157"
    },
    {
      "title": "钱包模拟器.APK",
      "link": "https://pan.quark.cn/s/89cf200e4b8e"
    },
    {
      "title": "syxz_1_0_8.apk",
      "link": "https://pan.quark.cn/s/dec76853b6f4"
    },
    {
      "title": "_票根标签生成器_v1.1.1.apk",
      "link": "https://pan.quark.cn/s/e2e22b95bdeb"
    },
    {
      "title": "Thunder-HTTPS 迅雷链接秒转 HTTP 专属链瞬间变通用",
      "link": "https://pan.quark.cn/s/b8d77a9cfad1"
    },
    {
      "title": "日语U学院至尊版.apk",
      "link": "https://pan.quark.cn/s/8ae0f6f1e901"
    },
    {
      "title": "流利说阅读.apk",
      "link": "https://pan.quark.cn/s/edc41dd90544"
    },
    {
      "title": "SpamBlocker",
      "link": "https://pan.quark.cn/s/e29958951b86"
    },
    {
      "title": "qldct105.apk",
      "link": "https://pan.quark.cn/s/f9016fe38d2f"
    },
    {
      "title": "小薇直播(纯净版)_2.7.0.3.apk",
      "link": "https://pan.quark.cn/s/dabed9b323cb"
    },
    {
      "title": "微众_1.2.apk",
      "link": "https://pan.quark.cn/s/e443b2bbc4ee"
    },
    {
      "title": "车来了 4.66.0去广告版_辰夕.apk",
      "link": "https://pan.quark.cn/s/1bc585468d88"
    },
    {
      "title": "NP管理器 3.1.23.apk",
      "link": "https://pan.quark.cn/s/44ad92c4611c"
    },
    {
      "title": "AppLock应用锁 5.13.2解锁VIP_Mixroot.apk",
      "link": "https://pan.quark.cn/s/f7c6bf4b0cba"
    },
    {
      "title": "开发助手 8.8.0-ng专业版_鹿蜀.apk",
      "link": "https://pan.quark.cn/s/a7302a656abd"
    },
    {
      "title": "乐秀录屏大师 8.2.1.0解锁VIP_NURIK.apk",
      "link": "https://pan.quark.cn/s/e92f64acb081"
    },
    {
      "title": "4396-城市竞赛：方块流行益智游戏-『精选Switch游戏』",
      "link": "https://pan.quark.cn/s/0a456b2a6d3d"
    },
    {
      "title": "2678-公民团结起来：地球x空间-『精选Switch游戏』",
      "link": "https://pan.quark.cn/s/e4151e8155d5"
    },
    {
      "title": "【光环国际】2024软考高级系统分析师VIP套餐",
      "link": "https://pan.quark.cn/s/6ff105e0180f"
    },
    {
      "title": "记得记账 0.48.1会员版_辰夕.apk",
      "link": "https://pan.quark.cn/s/26934b5cb65e"
    },
    {
      "title": "追剧吧 1.5.6.2去广告版_落北.apk",
      "link": "https://pan.quark.cn/s/732f168667d4"
    },
    {
      "title": "快捷记账 4.9.42专业版_NURIK.apk",
      "link": "https://pan.quark.cn/s/881cd45ab589"
    },
    {
      "title": "一叶日记 2.10.0会员版_辰夕.apk",
      "link": "https://pan.quark.cn/s/40a43454d2aa"
    },
    {
      "title": "微商管家 1.1.9会员版_鹿蜀.apk",
      "link": "https://pan.quark.cn/s/f66c1677961b"
    }
  ]
}