{
  "source": "https://pan.52wei.cc/categories.php?id=5",
  "file_index": 382,
  "total": 100,
  "items": [
    {
      "title": "《爱思唯尔科学哲学手册(套装共9卷16册) 》【448.1 MB】",
      "link": "https://pan.quark.cn/s/7e49f3bbc506"
    },
    {
      "title": "108个必懂的思维模型，精美图解电子版PPT【PDF】",
      "link": "https://pan.quark.cn/s/e886338b6ead"
    },
    {
      "title": "《第五项修炼（套装共5册） 》【44.7 MB】",
      "link": "https://pan.quark.cn/s/74f5280c8d5f"
    },
    {
      "title": "大叔英语 Coach Shane",
      "link": "https://pan.quark.cn/s/ecf9ce00e430"
    },
    {
      "title": "《诺贝尔文学奖大师作品集(套装共19册) 》【4.2 MB】",
      "link": "https://pan.quark.cn/s/e0862999e9e5"
    },
    {
      "title": "樊登读书推荐100本",
      "link": "https://pan.quark.cn/s/f600e1d3fa73"
    },
    {
      "title": "《未读哲学小经典·思想家（套装五册） 》【5.0 MB】",
      "link": "https://pan.quark.cn/s/cec34857fe76"
    },
    {
      "title": "钱儿爸全集",
      "link": "https://pan.quark.cn/s/17a89246497e"
    },
    {
      "title": "《童年中国(套装5册) 》【26.1 MB】",
      "link": "https://pan.quark.cn/s/ebf374790ccd"
    },
    {
      "title": "《初学记：新国学·大语文(全5册) 》【41.3 MB】",
      "link": "https://pan.quark.cn/s/ad2240e23e99"
    },
    {
      "title": "1-2年级 《看图写话课》 基础篇 提高篇",
      "link": "https://pan.quark.cn/s/40991b6cbc6f"
    },
    {
      "title": "《PPT速成手册70讲：创造出含金量达100万的PPT 》【1.03 GB】",
      "link": "https://pan.quark.cn/s/955f3dbee76b"
    },
    {
      "title": "3-6年级 《同步作文课》让孩子轻松写作",
      "link": "https://pan.quark.cn/s/31d89f72453f"
    },
    {
      "title": "《2021年1980页PPT设计灵感手册 》【4.38 GB】",
      "link": "https://pan.quark.cn/s/e55878b5d36e"
    },
    {
      "title": "337【喜马拉雅】朱伟21天英语单词速记营(2000词)",
      "link": "https://pan.quark.cn/s/e59591098ca6"
    },
    {
      "title": "《胡小闹爆笑脱口秀：千古名句篇 》 (198集)【小学~音频】",
      "link": "https://pan.quark.cn/s/7fc438b3a422"
    },
    {
      "title": "《中国诗词公开课[全2册] 》【12.5 MB】",
      "link": "https://pan.quark.cn/s/cb2e8e761448"
    },
    {
      "title": "《中华文化与中医学丛书[共15册] 》【23.1 MB】",
      "link": "https://pan.quark.cn/s/f99ad8361aa3"
    },
    {
      "title": "世界历史 CCTV纪录片1-100集【小初高~视频】",
      "link": "https://pan.quark.cn/s/7660632f41bf"
    },
    {
      "title": "《天下霸唱 》【74.4 MB】",
      "link": "https://pan.quark.cn/s/b38dc3d136a1"
    },
    {
      "title": "《不一样的中国史·全13册 》【275.3 MB】",
      "link": "https://pan.quark.cn/s/f4b887c3d314"
    },
    {
      "title": "读霸（小学英语阅读128篇）",
      "link": "https://pan.quark.cn/s/45128209ed20"
    },
    {
      "title": "《史记 (套装共6册) 》【50.0 MB】",
      "link": "https://pan.quark.cn/s/623b67224e48"
    },
    {
      "title": "儿童冒险喜剧动画片《皮皮布布环游世界 Pipi pupu",
      "link": "https://pan.quark.cn/s/d361ef3c79c2"
    },
    {
      "title": "《半小时漫画文学系列10册 》【432.1 MB】",
      "link": "https://pan.quark.cn/s/5ca1d80d70a0"
    },
    {
      "title": "超级表达课，你的表达价值千万，会说话成大事【家长课堂~视频】",
      "link": "https://pan.quark.cn/s/273cd25986fa"
    },
    {
      "title": "《抖音营销系统：未来抖商 - 解密从0到1亿粉丝的实操路径！深度剖析抖音营销全系统策略！ 》【30.8 MB】",
      "link": "https://pan.quark.cn/s/eca6a0c43157"
    },
    {
      "title": "《木苏里合集（14本） 》【6.6 MB】",
      "link": "https://pan.quark.cn/s/c8cbc9c055af"
    },
    {
      "title": "Penelope 《蓝色小考拉》中英文动画合集 英语零基础必看",
      "link": "https://pan.quark.cn/s/ea41349811b4"
    },
    {
      "title": "《半小时漫画中国史大全集 0-5 番外篇（共7册） 》【295.9 MB】",
      "link": "https://pan.quark.cn/s/946e47657ac4"
    },
    {
      "title": "【见物能聊】100个常见物品每日亲子英语词汇视频",
      "link": "https://pan.quark.cn/s/d514bff684a8"
    },
    {
      "title": "《Word联盟 PowerPoint2013视频教程全套 》【637.1 MB】",
      "link": "https://pan.quark.cn/s/b4beff508381"
    },
    {
      "title": "《汉译世界历史学术名著丛书（套装24册） 》【62.5 MB】",
      "link": "https://pan.quark.cn/s/d98e67ee4261"
    },
    {
      "title": "保林叔叔讲故事音频集",
      "link": "https://pan.quark.cn/s/0d56eb733a2a"
    },
    {
      "title": "《连环画_老夫子（28册） 》【307.1 MB】",
      "link": "https://pan.quark.cn/s/919c85362d1e"
    },
    {
      "title": "18.曹林权-思维导图单词大课（视频课+课件）",
      "link": "https://pan.quark.cn/s/b5bbc0cc91fe"
    },
    {
      "title": "66.田老师英语大揭秘",
      "link": "https://pan.quark.cn/s/ff583b5c1432"
    },
    {
      "title": "《食罪者（大全集共10册） 》【6.7 MB】",
      "link": "https://pan.quark.cn/s/e68ade7d8936"
    },
    {
      "title": "《三津田信三经典推理小说集[套装共四册] 》【4.1 MB】",
      "link": "https://pan.quark.cn/s/960ad4047616"
    },
    {
      "title": "B站 来自美国的周树华《英语零基础直达口语流利》【完结】",
      "link": "https://pan.quark.cn/s/987a91e36fc0"
    },
    {
      "title": "《残雪经典作品集（共30册） 》【96.0 MB】",
      "link": "https://pan.quark.cn/s/1980ffce3ecb"
    },
    {
      "title": "Ellen老师《从零开始学英语语法视频课程》",
      "link": "https://pan.quark.cn/s/9589adb5c6da"
    },
    {
      "title": "《漫画乌龙院大合集 》【4.55 GB】",
      "link": "https://pan.quark.cn/s/02db8150debb"
    },
    {
      "title": "荷花老师《用耳朵学英语》(2)",
      "link": "https://pan.quark.cn/s/f3e5cff82b3f"
    },
    {
      "title": "《世界名著大师课合集柳鸣九等 》【51.6 MB】",
      "link": "https://pan.quark.cn/s/1596e94b7ea8"
    },
    {
      "title": "《外国名著小说合集（套装14册） 》【36.9 MB】",
      "link": "https://pan.quark.cn/s/7ddc5f1e51a0"
    },
    {
      "title": "马方旭Alex《口语达人-流利说英语的秘笈》",
      "link": "https://pan.quark.cn/s/339bed8f7837"
    },
    {
      "title": "《你一定要知道的心理常识全集破解行为背后的心理奥秘 》【115.2 MB】",
      "link": "https://pan.quark.cn/s/ae9cef161648"
    },
    {
      "title": "《中国历史悬疑系列（套装共5册） 深入描述、解析、破译重大的历史谜案，再现历史的变幻与丰富 》【55.0 MB】",
      "link": "https://pan.quark.cn/s/13e53d82523b"
    },
    {
      "title": "颠覆传统的英语蜕变课（完结）",
      "link": "https://pan.quark.cn/s/54bbd0510e6c"
    },
    {
      "title": "《中国古典文学名著100部珍藏版 》【389.9 MB】",
      "link": "https://pan.quark.cn/s/90d4f9f6dd5f"
    },
    {
      "title": "名师到家视频课1-6年",
      "link": "https://pan.quark.cn/s/8030e3d5bc86"
    },
    {
      "title": "《飞卢网·小说·精选 》【366.2 MB】",
      "link": "https://pan.quark.cn/s/bd714cb0a860"
    },
    {
      "title": "看图写话视频课程",
      "link": "https://pan.quark.cn/s/17fafea83f3d"
    },
    {
      "title": "《飞卢小说(568部) 》【366.2 MB】",
      "link": "https://pan.quark.cn/s/bb419218c15a"
    },
    {
      "title": "「《新东方雅思全能7分旗舰外教VIP全程班》课程官方售价4880元」",
      "link": "https://pan.quark.cn/s/ebb00f9a826d"
    },
    {
      "title": "《豆瓣高分经管好书（共11册） 》【96.7 MB】",
      "link": "https://pan.quark.cn/s/01a24517bfe0"
    },
    {
      "title": "《资治通鉴·附考异（全六册） 》【16.5 MB】",
      "link": "https://pan.quark.cn/s/c4185cfa9026"
    },
    {
      "title": "26春 典中点 三~6年级英语下（JJ版）",
      "link": "https://pan.quark.cn/s/23b95a047f46"
    },
    {
      "title": "学而思大阅读+伴读书房+电子书 L1",
      "link": "https://pan.quark.cn/s/2bd7ec7d59ac"
    },
    {
      "title": "《世界史的拼图7册 》【126.9 MB】",
      "link": "https://pan.quark.cn/s/8c174ee6e8a4"
    },
    {
      "title": "《陷入校草弟弟的套路 》【489.5 MB】",
      "link": "https://pan.quark.cn/s/b277cc0a8cb8"
    },
    {
      "title": "学而思大阅读+伴读书房+电子书 L2",
      "link": "https://pan.quark.cn/s/61b0a8a01f74"
    },
    {
      "title": "《全套人民币彩色版图鉴[doc] 》【22.2 MB】",
      "link": "https://pan.quark.cn/s/db2406bdee4c"
    },
    {
      "title": "学而思大阅读+伴读书房+电子书 L3",
      "link": "https://pan.quark.cn/s/39ac94cfbc7b"
    },
    {
      "title": "《2021年度畅销历史精选集套装13册 本本好书[pdf] 》【90.7 MB】",
      "link": "https://pan.quark.cn/s/ffd8798c6f5b"
    },
    {
      "title": "学而思大阅读+伴读书房+电子书 L4",
      "link": "https://pan.quark.cn/s/0c976bf0e9b3"
    },
    {
      "title": "《豆瓣2024年度读书榜单 》【781.4 MB】",
      "link": "https://pan.quark.cn/s/d63b6c0ad8e0"
    },
    {
      "title": "学而思大阅读+伴读书房+电子书 L5",
      "link": "https://pan.quark.cn/s/e57fd00be30b"
    },
    {
      "title": "《付费小说300 》【346.1 MB】",
      "link": "https://pan.quark.cn/s/b7db326962cb"
    },
    {
      "title": "学而思大阅读+伴读书房+电子书 L6",
      "link": "https://pan.quark.cn/s/b69437ca0439"
    },
    {
      "title": "《世界文学名著合集（60册） 》【172.3 MB】",
      "link": "https://pan.quark.cn/s/5ff02b89fa81"
    },
    {
      "title": "26春 典中点 三~6年级英语下（R-pep版）",
      "link": "https://pan.quark.cn/s/8f27a1191b19"
    },
    {
      "title": "《U君·赢在8小时之外付费文章（绝密，勿外传） 》【731.9 MB】",
      "link": "https://pan.quark.cn/s/fd994aa1a885"
    },
    {
      "title": "《中国茶文化（彩图修订本）王玲 》【27.8 MB】",
      "link": "https://pan.quark.cn/s/cb8a22212942"
    },
    {
      "title": "数学《典中点（抢先版）》北师 26春",
      "link": "https://pan.quark.cn/s/5f4d54dacc84"
    },
    {
      "title": "《我们生活在巨大的差距里 (余华) 》【1.4 MB】",
      "link": "https://pan.quark.cn/s/14301e3fd61d"
    },
    {
      "title": "根源数学满分宝典（1年级）",
      "link": "https://pan.quark.cn/s/9e9064c00795"
    },
    {
      "title": "《陕西自助旅游快易通！ 》【108.3 MB】",
      "link": "https://pan.quark.cn/s/b3e3eb85c272"
    },
    {
      "title": "《事业编公基知识点 》【571.3 MB】",
      "link": "https://pan.quark.cn/s/5f39fb421794"
    },
    {
      "title": "根源数学满分宝典（2年级）",
      "link": "https://pan.quark.cn/s/2e6e524cbfa2"
    },
    {
      "title": "《2023年JJ完结金榜1-50 》【6.1 MB】",
      "link": "https://pan.quark.cn/s/6a54c3398742"
    },
    {
      "title": "《十万个为什么各版本大合集 》【4.83 GB】",
      "link": "https://pan.quark.cn/s/66c5e44404ef"
    },
    {
      "title": "根源数学满分宝典（3年级）",
      "link": "https://pan.quark.cn/s/daffb12e9311"
    },
    {
      "title": "《柏杨版通鉴纪事本末(共19部) 》【201.7 MB】",
      "link": "https://pan.quark.cn/s/9b6f1f0d6a51"
    },
    {
      "title": "《补肾壮阳秘方大全 》【520.6 MB】",
      "link": "https://pan.quark.cn/s/8fe5a0e5b4cd"
    },
    {
      "title": "《知识星球 付费课程（400篇）--全是干货 》【609.2 MB】",
      "link": "https://pan.quark.cn/s/5f736943841a"
    },
    {
      "title": "《知识星球·付费课程（400篇） 》【963.7 MB】",
      "link": "https://pan.quark.cn/s/d51e502996b3"
    },
    {
      "title": "《樊登读书推荐500册 》【6.86 GB】",
      "link": "https://pan.quark.cn/s/0e68eaeca9c1"
    },
    {
      "title": "《儿童文化历史启蒙藏在地图里的古诗词 (PDF 音频) 》【715.3 MB】",
      "link": "https://pan.quark.cn/s/eef9d63e25e4"
    },
    {
      "title": "《被收录至大英图书馆中文馆的16本中国网文- 》【3.2 MB】",
      "link": "https://pan.quark.cn/s/6f7ef96459dd"
    },
    {
      "title": "《中国古代历史图谱 》【1008.4 MB】",
      "link": "https://pan.quark.cn/s/77d5850070f1"
    },
    {
      "title": "《美国史：世界中心的岛 奠基者 革命之夏 美国官僚体制 美国大外交（全5册） 》【35.2 MB】",
      "link": "https://pan.quark.cn/s/b9f3e8ae7126"
    },
    {
      "title": "《象吉通书 魏明远 》【140.5 MB】",
      "link": "https://pan.quark.cn/s/3fac86113f0c"
    },
    {
      "title": "《中华传世藏书系列丛书 》【610.6 MB】",
      "link": "https://pan.quark.cn/s/9c2636711353"
    },
    {
      "title": "《宫部美雪经典作品全集（共18册） 》【42.0 MB】",
      "link": "https://pan.quark.cn/s/c89ebd3fe41b"
    },
    {
      "title": "《财运风水学 邵伟华 》【15.9 MB】",
      "link": "https://pan.quark.cn/s/ef3b38ce616e"
    },
    {
      "title": "《战略管理第二版 魏章 》【29.0 MB】",
      "link": "https://pan.quark.cn/s/dda562ab7794"
    },
    {
      "title": "《汤因比历史著作集（共7册） 》【22.9 MB】",
      "link": "https://pan.quark.cn/s/5e773e4a6942"
    },
    {
      "title": "《中国社会科学博士论文文库 》【2.47 GB】",
      "link": "https://pan.quark.cn/s/90d7c4c836c5"
    }
  ]
}