{
  "source": "https://pan.52wei.cc/categories.php?id=3",
  "category": "电子书",
  "file_index": 44,
  "total": 100,
  "items": [
    {
      "title": "人生若只初相见-亚马逊高分书籍",
      "link": "https://pan.baidu.com/s/17NcCsb1r_JOlFYmuI7jeaQ?pwd=lrfe"
    },
    {
      "title": "罹伤－－跌停的青春-亚马逊高分书籍",
      "link": "https://pan.baidu.com/s/1dgnnmWB58prrFQn7VjuHkA?pwd=jxtt"
    },
    {
      "title": "有一种爱情叫兄弟III-亚马逊高分书籍",
      "link": "https://pan.baidu.com/s/1P1o8lnxY4exr4lrKgM_ZGQ?pwd=iv31"
    },
    {
      "title": "直到最后一句-亚马逊高分书籍",
      "link": "https://pan.baidu.com/s/1YZFzzfQ1aRhEVQhVUY02GQ?pwd=9lps"
    },
    {
      "title": "女友20年珍藏（2006-2008）-亚马逊高分书籍",
      "link": "https://pan.baidu.com/s/1u8-Bbaa74GGX2qh1h-JILg?pwd=vkqs"
    },
    {
      "title": "恋风恋歌-亚马逊高分书籍",
      "link": "https://pan.baidu.com/s/1Zbto-CCDGGt9xoTHynzHNg?pwd=ves2"
    },
    {
      "title": "上海，不哭！-亚马逊高分书籍",
      "link": "https://pan.baidu.com/s/1QS7HaDXBPMiVMKEufVGd_g?pwd=i3bp"
    },
    {
      "title": "如果梦醒时还在一起-亚马逊高分书籍",
      "link": "https://pan.baidu.com/s/1IXHb1YZiVxaDMW-iotmSfQ?pwd=5ycn"
    },
    {
      "title": "午门窘事1-亚马逊高分书籍",
      "link": "https://pan.baidu.com/s/1_WHB34mKDBOLbIemx5wTeg?pwd=9q48"
    },
    {
      "title": "我们不再纯真的年代-亚马逊高分书籍",
      "link": "https://pan.baidu.com/s/1UvW3CdzuNgrzf3Fw1xHt4Q?pwd=i3u9"
    },
    {
      "title": "王陵美人：冲击新言情时代-亚马逊高分书籍",
      "link": "https://pan.baidu.com/s/1E43UmjbfBS0bzXZWy011AA?pwd=lpwj"
    },
    {
      "title": "亲爱的永远亲爱-亚马逊高分书籍",
      "link": "https://pan.baidu.com/s/1OiSeeuNYdnxbc5pPiNNs4g?pwd=8mih"
    },
    {
      "title": "别离歌——80后女子的《半生缘》-亚马逊高分书籍",
      "link": "https://pan.baidu.com/s/14B8e3qo3NU57u9M4NAN9jQ?pwd=zmya"
    },
    {
      "title": "景，我爱你-亚马逊高分书籍",
      "link": "https://pan.baidu.com/s/1WR-ljX6KxyzO-FN9UNnA2Q?pwd=ax7o"
    },
    {
      "title": "花是微笑的草-亚马逊高分书籍",
      "link": "https://pan.baidu.com/s/1PsKoiwWx9sLvIcBXWgL3EA?pwd=u902"
    },
    {
      "title": "毕业一年贱-亚马逊高分书籍",
      "link": "https://pan.baidu.com/s/1m9dKEujmx4pRZSRuR5_apg?pwd=iqxm"
    },
    {
      "title": "废墟下的青春-亚马逊高分书籍",
      "link": "https://pan.baidu.com/s/1sZ_vRuJblgDGYseaHx3emg?pwd=b4mj"
    },
    {
      "title": "因缘妙美人-亚马逊高分书籍",
      "link": "https://pan.baidu.com/s/1dAXXSXsXTxOMNkhU_U3etg?pwd=anq6"
    },
    {
      "title": "色已成空-亚马逊高分书籍",
      "link": "https://pan.baidu.com/s/1GNivdFFiWVt2jBBlpzMs7w?pwd=0wl6"
    },
    {
      "title": "下辈子，我要预约爱情-亚马逊高分书籍",
      "link": "https://pan.baidu.com/s/1uC1o1f64-tvcvsXPkwQ6TA?pwd=fz08"
    },
    {
      "title": "第一次爱的人-亚马逊高分书籍",
      "link": "https://pan.baidu.com/s/1d1zZcyfF6sgt5Ui0haLtXw?pwd=jc40"
    },
    {
      "title": "太平-亚马逊高分书籍",
      "link": "https://pan.baidu.com/s/16tc20nbYtmmXQfMYpZ01pw?pwd=48g5"
    },
    {
      "title": "盛夏江南-亚马逊高分书籍",
      "link": "https://pan.baidu.com/s/1BWhWj9qFjp9R09S6_6Z2ng?pwd=nl7p"
    },
    {
      "title": "蜜恋三次方-亚马逊高分书籍",
      "link": "https://pan.baidu.com/s/1AuB3bvd4hOx4WtXvep1cwg?pwd=dtjw"
    },
    {
      "title": "蝶葬-亚马逊高分书籍",
      "link": "https://pan.baidu.com/s/1wORwL3EFL_uiBGrrhVT_VQ?pwd=9eil"
    },
    {
      "title": "千山万水人海中（下）-亚马逊高分书籍",
      "link": "https://pan.baidu.com/s/1DWW66rly__4fYNu3EGUKFg?pwd=pc4w"
    },
    {
      "title": "我的高中①——谜失课室-亚马逊高分书籍",
      "link": "https://pan.baidu.com/s/107Erd97awCkrgSm1F2yXeA?pwd=8tq2"
    },
    {
      "title": "情人-亚马逊高分书籍",
      "link": "https://pan.baidu.com/s/1MPVqsKNSrgYtw5zfygOSDA?pwd=xp5w"
    },
    {
      "title": "要有多勇敢，才能念念不忘-亚马逊高分书籍",
      "link": "https://pan.baidu.com/s/1K9YjOhmtmzoVN3Z6rgoQvg?pwd=pbqp"
    },
    {
      "title": "幸福女儿成长记-亚马逊高分书籍",
      "link": "https://pan.baidu.com/s/1zKDVXA-en7SKLR6tLSFpVA?pwd=n6yd"
    },
    {
      "title": "六朝纪事之我主沉浮-亚马逊高分书籍",
      "link": "https://pan.baidu.com/s/1x3_lhMCW1zpkWDggpkxHEA?pwd=4ngf"
    },
    {
      "title": "会飞的泪珠-亚马逊高分书籍",
      "link": "https://pan.baidu.com/s/1S4TMpr7qP2B8QjYnVN8mZg?pwd=s1ue"
    },
    {
      "title": "千杯不醉-亚马逊高分书籍",
      "link": "https://pan.baidu.com/s/1sewZlOeV548ROa6hlVhEDw?pwd=y6kx"
    },
    {
      "title": "泪茧-亚马逊高分书籍",
      "link": "https://pan.baidu.com/s/1Uiiwvw9vVsp2HGD1NoAygQ?pwd=c162"
    },
    {
      "title": "媚行深宫——荷泽天下-亚马逊高分书籍",
      "link": "https://pan.baidu.com/s/1-hvTwSFOcUKIcF4E-o_xZg?pwd=0cgv"
    },
    {
      "title": "叠年-亚马逊高分书籍",
      "link": "https://pan.baidu.com/s/1kfjldLlvqaOUXG3xxMzO3Q?pwd=whn8"
    },
    {
      "title": "苏旷传奇之重整河山待后生-亚马逊高分书籍",
      "link": "https://pan.baidu.com/s/1zFMEpP7NTZlvga8MrE_HMg?pwd=r3k3"
    },
    {
      "title": "第二季爱情-亚马逊高分书籍",
      "link": "https://pan.baidu.com/s/1_eYzNkBJPRUBA8-_qqLGug?pwd=1b43"
    },
    {
      "title": "王子与丑女的爱情：优柔王子之歌-亚马逊高分书籍",
      "link": "https://pan.baidu.com/s/1ZmHRaWdjlccFiyIV8RxmcA?pwd=i5cu"
    },
    {
      "title": "巫山传：看绝美女侠姬瑶花如何一统巫山门-亚马逊高分书籍",
      "link": "https://pan.baidu.com/s/1XcJjcM6WCM9GiKHKhotZ0g?pwd=57cf"
    },
    {
      "title": "山那边是海-亚马逊高分书籍",
      "link": "https://pan.baidu.com/s/1ty3E1FzYvpUgU90OMlihcw?pwd=e5mm"
    },
    {
      "title": "《花与爱丽丝》Vol6 以太-亚马逊高分书籍",
      "link": "https://pan.baidu.com/s/1MglMoQSqIP5cR7pKy1VDiw?pwd=e1v3"
    },
    {
      "title": "往事如烟-亚马逊高分书籍",
      "link": "https://pan.baidu.com/s/1_bYG0xVjl328Bt0dnaOoTg?pwd=1237"
    },
    {
      "title": "爱你，就算全世界与我为敌-亚马逊高分书籍",
      "link": "https://pan.baidu.com/s/1OAnvDCVXJv_nrtOLgJ8k8A?pwd=iwsa"
    },
    {
      "title": "天下倾歌-亚马逊高分书籍",
      "link": "https://pan.baidu.com/s/1km3-XFcmhyIs7SqPI5FiLQ?pwd=9uis"
    },
    {
      "title": "桃花乱-亚马逊高分书籍",
      "link": "https://pan.baidu.com/s/1_4ASMGYxwoSqdebH2AnGaQ?pwd=ytzt"
    },
    {
      "title": "夜上海·终结篇-亚马逊高分书籍",
      "link": "https://pan.baidu.com/s/1Y89XUX0fmtB0W0T8r2TIsw?pwd=eeeh"
    },
    {
      "title": "沥川往事-亚马逊高分书籍",
      "link": "https://pan.baidu.com/s/1mmwVLv-EQfBA5rjQ6ZPlXw?pwd=4deh"
    },
    {
      "title": "流光飞舞-亚马逊高分书籍",
      "link": "https://pan.baidu.com/s/1GljbXCo3MfftX49seYs_Zw?pwd=7abf"
    },
    {
      "title": "微雪-亚马逊高分书籍",
      "link": "https://pan.baidu.com/s/1BYlJC2_PMiX_TqkM-UoAlg?pwd=6t89"
    },
    {
      "title": "普兰誓言-亚马逊高分书籍",
      "link": "https://pan.baidu.com/s/1WSLDEiUwT-L8xB39U6SFNQ?pwd=489d"
    },
    {
      "title": "武林萌主（终结篇）-亚马逊高分书籍",
      "link": "https://pan.baidu.com/s/1KQ6o-HUdudwwKcXPnEPG0g?pwd=ob3k"
    },
    {
      "title": "宦倾城-亚马逊高分书籍",
      "link": "https://pan.baidu.com/s/1Vo3Mp6c_xOSaQEOduDkrng?pwd=uvlb"
    },
    {
      "title": "奉旨休夫-亚马逊高分书籍",
      "link": "https://pan.baidu.com/s/1V_yvA78LpFABJEDG7D_XFg?pwd=uwm7"
    },
    {
      "title": "冰莲花-亚马逊高分书籍",
      "link": "https://pan.baidu.com/s/1g59mzVwoTVZzHb9sMnKxCQ?pwd=kihj"
    },
    {
      "title": "嗨，我的男人-亚马逊高分书籍",
      "link": "https://pan.baidu.com/s/139wjiMpQCoov5YN4uywmSg?pwd=cls0"
    },
    {
      "title": "90季-我用整个宇宙来忘记你-亚马逊高分书籍",
      "link": "https://pan.baidu.com/s/1nIpRRGa6_2ZLksKb2WvJ1w?pwd=qwdm"
    },
    {
      "title": "半熟-亚马逊高分书籍",
      "link": "https://pan.baidu.com/s/1G_B6j3FfyZmUMu3Ktp5NlQ?pwd=kp3e"
    },
    {
      "title": "槑女囧事：三个80后女生的成长日记-亚马逊高分书籍",
      "link": "https://pan.baidu.com/s/1tYYMRRG-OCHhA1j3kHflGw?pwd=qio6"
    },
    {
      "title": "戒爱-亚马逊高分书籍",
      "link": "https://pan.baidu.com/s/1zlRHOXvBSOfMHDYAtz91gQ?pwd=k8a2"
    },
    {
      "title": "鲈鱼-亚马逊高分书籍",
      "link": "https://pan.baidu.com/s/1Ly6jrQpqZ6U2ynlFOGC-_g?pwd=e02u"
    },
    {
      "title": "朝露若颜-亚马逊高分书籍",
      "link": "https://pan.baidu.com/s/1c35Z93QH2jAqnUZkJS9tkg?pwd=p1o4"
    },
    {
      "title": "流年明媚·相思谋-亚马逊高分书籍",
      "link": "https://pan.baidu.com/s/1uRQv8VMzB-f7Vva_PJdj6g?pwd=rszz"
    },
    {
      "title": "梨花雪后（上）-亚马逊高分书籍",
      "link": "https://pan.baidu.com/s/1aMHuXptMkQDOAF9T0jYQAQ?pwd=w9i5"
    },
    {
      "title": "图南志-亚马逊高分书籍",
      "link": "https://pan.baidu.com/s/11ZRjp3k2bB-DrQkyeU1aug?pwd=n7vg"
    },
    {
      "title": "匆匆那年（下）-亚马逊高分书籍",
      "link": "https://pan.baidu.com/s/1Mhlc4PSm9c4wUzTwVCQFWw?pwd=9osw"
    },
    {
      "title": "荒野侦探-亚马逊高分书籍",
      "link": "https://pan.baidu.com/s/1ul3isA0HxY0zLrrjN2qHbQ?pwd=8fly"
    },
    {
      "title": "锦瑟无端-亚马逊高分书籍",
      "link": "https://pan.baidu.com/s/1OFj1uDVg0XGaAkgRKC85Yg?pwd=tfu3"
    },
    {
      "title": "宝器江湖-亚马逊高分书籍",
      "link": "https://pan.baidu.com/s/1VgS-VL38a0_UN-9WYhgicQ?pwd=xvmj"
    },
    {
      "title": "未央歌：40年来最感动我们的书-亚马逊高分书籍",
      "link": "https://pan.baidu.com/s/1ZR7PJgYDz0wlfRZCv64KnA?pwd=z578"
    },
    {
      "title": "今生注定我和你-亚马逊高分书籍",
      "link": "https://pan.baidu.com/s/1j68FvQW7c401lZvxSekNVA?pwd=yaw9"
    },
    {
      "title": "除了我你还能爱谁-亚马逊高分书籍",
      "link": "https://pan.baidu.com/s/1qVLVS24iuigDVJBfoD0R6A?pwd=8lny"
    },
    {
      "title": "转角·爱·流年-亚马逊高分书籍",
      "link": "https://pan.baidu.com/s/13XTNGchC2Y--6RjrzY1z7g?pwd=1x6c"
    },
    {
      "title": "疯长系-亚马逊高分书籍",
      "link": "https://pan.baidu.com/s/1Sv1lR1xp38--WyApbPrYkA?pwd=4ifl"
    },
    {
      "title": "沙僧日记2-亚马逊高分书籍",
      "link": "https://pan.baidu.com/s/1q6f0LSdeDRgu0prDjdEkfQ?pwd=280g"
    },
    {
      "title": "穿过青春所有迷路的日子-亚马逊高分书籍",
      "link": "https://pan.baidu.com/s/1OSMDjUHZsK2n0tss2kNdVw?pwd=rrnz"
    },
    {
      "title": "封印之书·镜之门2-亚马逊高分书籍",
      "link": "https://pan.baidu.com/s/1ii7_sgENag2HaAWWtGeIQw?pwd=75v1"
    },
    {
      "title": "乱世太子妃-亚马逊高分书籍",
      "link": "https://pan.baidu.com/s/1_yRkJGK8Zz9I1v4XclUFjA?pwd=s38g"
    },
    {
      "title": "寂寞是青春的墓志铭-亚马逊高分书籍",
      "link": "https://pan.baidu.com/s/15lW0UuwZX22AXwlyHEB_Mw?pwd=l9c3"
    },
    {
      "title": "相思王妃-亚马逊高分书籍",
      "link": "https://pan.baidu.com/s/1CE4airnc8-srPnoITOf2QQ?pwd=zmb3"
    },
    {
      "title": "第一最好不相见-亚马逊高分书籍",
      "link": "https://pan.baidu.com/s/1QE_whscNujPhxRlzqXpJlg?pwd=wig0"
    },
    {
      "title": "走路去巴黎：纯情少女奋斗史-亚马逊高分书籍",
      "link": "https://pan.baidu.com/s/1WqbxHICz-CN9OQ14An3LHg?pwd=48gq"
    },
    {
      "title": "追爱症候群①-亚马逊高分书籍",
      "link": "https://pan.baidu.com/s/1kpcFeaXIcwr4b3NSfVDwYw?pwd=lh9m"
    },
    {
      "title": "奔跑的蜗牛-亚马逊高分书籍",
      "link": "https://pan.baidu.com/s/1Dfkxw0d8GHsrrcA_IhqWoQ?pwd=tpcj"
    },
    {
      "title": "陪我跳舞吧-亚马逊高分书籍",
      "link": "https://pan.baidu.com/s/1nv6roh1SDPfVB4xrzeuO9w?pwd=m3wv"
    },
    {
      "title": "蜗牛姑娘勇敢向前走-亚马逊高分书籍",
      "link": "https://pan.baidu.com/s/1WQpbwnZ1a3JLtN-TgkHX3w?pwd=i300"
    },
    {
      "title": "王的校园之女仆爱上王-亚马逊高分书籍",
      "link": "https://pan.baidu.com/s/1ZYISdfzkV7_2H8YE0FpcaQ?pwd=cgqs"
    },
    {
      "title": "芙洛-亚马逊高分书籍",
      "link": "https://pan.baidu.com/s/16ToYIgl6jvatrMOCu_eHEg?pwd=5teo"
    },
    {
      "title": "80后先锋青春短篇小说集：零度叙述-亚马逊高分书籍",
      "link": "https://pan.baidu.com/s/1BLys5B-ruNFKX19SmSB64w?pwd=n02k"
    },
    {
      "title": "破罐子——一个80后的心灵自传-亚马逊高分书籍",
      "link": "https://pan.baidu.com/s/1X35L7tpAlnqliFM6Ka4U4g?pwd=b9c2"
    },
    {
      "title": "逐风流（下）-亚马逊高分书籍",
      "link": "https://pan.baidu.com/s/10k0YH32iPWaorI-SMtEu3A?pwd=1aa2"
    },
    {
      "title": "何以笙箫默-亚马逊高分书籍",
      "link": "https://pan.baidu.com/s/1rGEp2Vv3NS7M4kOL2ZrO8Q?pwd=nuge"
    },
    {
      "title": "我的活祖宗-亚马逊高分书籍",
      "link": "https://pan.baidu.com/s/16hvazWL0Yqk_Izps7iM7wA?pwd=afqs"
    },
    {
      "title": "我们用青春记住谁-亚马逊高分书籍",
      "link": "https://pan.baidu.com/s/1xl79vWQbeCwkAFGDt9iCcg?pwd=p5sv"
    },
    {
      "title": "小熊座少女-亚马逊高分书籍",
      "link": "https://pan.baidu.com/s/1BeQyxX1ctNWSl2tsbUk89Q?pwd=m7yf"
    },
    {
      "title": "穿越泰姬陵-亚马逊高分书籍",
      "link": "https://pan.baidu.com/s/1D8tq2FOPIIfej3WG0cQ9WA?pwd=ayp8"
    },
    {
      "title": "关于彼岸的一切-亚马逊高分书籍",
      "link": "https://pan.baidu.com/s/1snIEQ_fX7I-7z2YpwoxAOw?pwd=5nf1"
    },
    {
      "title": "大宫-亚马逊高分书籍",
      "link": "https://pan.baidu.com/s/1o_2RNQjE2WY70rJlPj0kYw?pwd=bqny"
    },
    {
      "title": "绿红妆之军营穿越（下）-亚马逊高分书籍",
      "link": "https://pan.baidu.com/s/1b0L0a2IDgXQ7hRI-bk7GwQ?pwd=t6go"
    },
    {
      "title": "美人谋·下-亚马逊高分书籍",
      "link": "https://pan.baidu.com/s/1qYN0NVKm3uNGNon6xopDRg?pwd=3d5p"
    }
  ]
}